nlp_augmentation/__init__.py
nlp_augmentation/char/__init__.py
nlp_augmentation/char/augmentor.py
nlp_augmentation/data/__init__.py
nlp_augmentation/data/qwerty_map.json
nlp_augmentation/data/slang.csv
nlp_augmentation/generate/__init__.py
nlp_augmentation/generate/generator.py
nlp_augmentation/text/__init__.py
nlp_augmentation/text/augmentor.py
nlp_augmentation/utils/__init__.py
nlp_augmentation/utils/lazy.py
nlp_augmentation/utils/resources.py
nlp_augmentation/utils/text_ops.py
nlp_augmentation/word/__init__.py
nlp_augmentation/word/augmentor.py
nlp_augmentation-1.1.1.dist-info/METADATA
nlp_augmentation-1.1.1.dist-info/WHEEL
nlp_augmentation-1.1.1.dist-info/top_level.txt
nlp_augmentation-1.1.1.dist-info/RECORD
