Metadata-Version: 2.4
Name: nlp_augmentation
Version: 1.1.1
Summary: Библиотека для аугментации текстовых данных на нескольких уровнях
Home-page: https://pypi.org/project/nlp_augmentation/
Author: Дима
Author-email: email@example.com
Project-URL: Source, https://github.com/dashof/nlp-augmentation
Project-URL: Tracker, https://github.com/dashof/nlp-augmentation/issues
Keywords: nlp augmentation text data augmentation machine learning
Classifier: Programming Language :: Python :: 3
Classifier: Programming Language :: Python :: 3.7
Classifier: Programming Language :: Python :: 3.8
Classifier: Programming Language :: Python :: 3.9
Classifier: Programming Language :: Python :: 3.10
Classifier: License :: OSI Approved :: MIT License
Classifier: Operating System :: OS Independent
Classifier: Topic :: Text Processing :: Linguistic
Classifier: Intended Audience :: Developers
Classifier: Intended Audience :: Science/Research
Requires-Python: >=3.8
Requires-Dist: packaging==25.0
Requires-Dist: numpy==1.26.4
Requires-Dist: beautifulsoup4==4.13.4
Requires-Dist: bs4==0.0.2
Requires-Dist: cloudpathlib==0.21.1
Requires-Dist: decorator==5.2.1
Requires-Dist: emoji==2.14.1
Requires-Dist: gensim==4.3.3
Requires-Dist: huggingface-hub==0.31.2
Requires-Dist: joblib==1.5.0
Requires-Dist: matplotlib==3.10.3
Requires-Dist: networkx==3.4.2
Requires-Dist: nltk==3.9.1
Requires-Dist: num2words==0.5.14
Requires-Dist: openpyxl==3.1.5
Requires-Dist: pandas==2.2.3
Requires-Dist: pyarrow==20.0.0
Requires-Dist: scikit-learn==1.6.1
Requires-Dist: scipy==1.13.1
Requires-Dist: seaborn==0.13.2
Requires-Dist: sentencepiece==0.2.0
Requires-Dist: spacy==3.8.4
Requires-Dist: text2digits==0.1.0
Requires-Dist: textblob==0.19.0
Requires-Dist: textsearch==0.0.24
Requires-Dist: tokenizers==0.21.1
Requires-Dist: toml==0.10.2
Requires-Dist: tqdm==4.67.1
Requires-Dist: transformers==4.51.3
Requires-Dist: urllib3==2.4.0
Requires-Dist: wordcloud==1.9.4
Requires-Dist: inflect==7.5.0
Requires-Dist: constituent_treelib==0.0.8
Dynamic: author
Dynamic: author-email
Dynamic: classifier
Dynamic: description
Dynamic: description-content-type
Dynamic: home-page
Dynamic: keywords
Dynamic: project-url
Dynamic: requires-dist
Dynamic: requires-python
Dynamic: summary
